Workbook

Sheet Input
B1: YFD FIRST AID TOOLS | F1: BUILDING FINANCIALLY HEALTHY GENERATION
F2: WHY DO PEOPLE TAKE CARE OF THEIR HEALTH, BUT NOT THEIR FINANCIAL HEALTH?
B3: First Financial Health Center Indonesia | F3: UBAH POLA PIKIR, PERBAIKI KEBIASAAN, DISIPLIN, WUJUDKAN MASA DEPAN
B5: YFD BASELINE
B10: No | C10: Tanggal | D10: Jenis | E10: Nominal | F10: Kategori | G10: Sifat | H10: Impulsive | I10: Mood Spending | J10: Keterangan | K10: Bucket
B11: 1 | C11: 46143 | D11: Pemasukan | E11: 7739000 | F11: Gaji | J11: UD BHM April | K11: =IFERROR(VLOOKUP(F11,Kategori_Mapping!$A:$B,2,FALSE()),"") -> Income
B12: 2 | C12: 46143 | D12: Pengeluaran | E12: 18500 | F12: Admin bank | G12: Need | H12: No | I12: Neutral | J12: BNI | K12: =IFERROR(VLOOKUP(F12,Kategori_Mapping!$A:$B,2,FALSE()),"") -> Essential Living
B13: 3 | C13: 46143 | D13: Pengeluaran | E13: 19000 | F13: YFD | G13: Need | H13: No | I13: Neutral | J13: YFD Telegram | K13: =IFERROR(VLOOKUP(F13,Kategori_Mapping!$A:$B,2,FALSE()),"") -> Future Building
B14: 4 | C14: 46143 | D14: Pengeluaran | E14: 300000 | F14: Sosial | G14: Need | H14: No | I14: Neutral | J14: Behel mega | K14: =IFERROR(VLOOKUP(F14,Kategori_Mapping!$A:$B,2,FALSE()),"") -> Flexible + Social
B15: 5 | C15: 46144 | D15: Pengeluaran | E15: 61700 | F15: Grab/maxime | G15: Need | H15: No | I15: Neutral | J15: HR ke St Regis | K15: =IFERROR(VLOOKUP(F15,Kategori_Mapping!$A:$B,2,FALSE()),"") -> Essential Living
B16: 6 | C16: 46145 | D16: Pengeluaran | E16: 80900 | F16: Skin care-beauty | G16: Need | H16: No | I16: Stressed | J16: Body care | K16: =IFERROR(VLOOKUP(F16,Kategori_Mapping!$A:$B,2,FALSE()),"") -> Flexible + Social
B17: 7 | C17: 46145 | D17: Pengeluaran | E17: 65920 | F17: Skin care-beauty | G17: Need | H17: Yes | I17: Stressed | J17: Exfoliating gloves | K17: =IFERROR(VLOOKUP(F17,Kategori_Mapping!$A:$B,2,FALSE()),"") -> Flexible + Social
B18: 8 | C18: 46146 | D18: Pemasukan | E18: 182477 | F18: Lain-lain | J18: Tiktok Live😱 | K18: =IFERROR(VLOOKUP(F18,Kategori_Mapping!$A:$B,2,FALSE()),"") -> Income
B19: 9 | C19: 46146 | D19: Pengeluaran | E19: 42000 | F19: Grab/maxime | G19: Need | H19: No | I19: Neutral | J19: ST regis ke kos | K19: =IFERROR(VLOOKUP(F19,Kategori_Mapping!$A:$B,2,FALSE()),"") -> Essential Living
B20: 10 | C20: 46146 | D20: Pengeluaran | E20: 19200 | F20: Grab/maxime | G20: Need | H20: No | I20: Neutral | J20: Kos ke kang abuy | K20: =IFERROR(VLOOKUP(F20,Kategori_Mapping!$A:$B,2,FALSE()),"") -> Essential Living
B21: 11 | C21: 46146 | D21: Pengeluaran | E21: 77000 | F21: Networking | G21: Need | H21: No | I21: Neutral | J21: Ketemu investor | K21: =IFERROR(VLOOKUP(F21,Kategori_Mapping!$A:$B,2,FALSE()),"") -> Future Building
B22: 12 | C22: 46146 | D22: Pengeluaran | E22: 12200 | F22: Grab/maxime | G22: Wants | H22: Yes | I22: Tired | J22: Ke BW | K22: =IFERROR(VLOOKUP(F22,Kategori_Mapping!$A:$B,2,FALSE()),"") -> Essential Living
B23: 13 | C23: 46146 | D23: Pengeluaran | E23: 134000 | F23: Hiburan | G23: Wants | H23: Yes | I23: Tired | J23: Makan stobery coco | K23: =IFERROR(VLOOKUP(F23,Kategori_Mapping!$A:$B,2,FALSE()),"") -> Flexible + Social
B24: 14 | C24: 46146 | D24: Pengeluaran | E24: 40000 | F24: Hiburan | G24: Wants | H24: Yes | I24: Tired | J24: Minum bir sambil sunset | K24: =IFERROR(VLOOKUP(F24,Kategori_Mapping!$A:$B,2,FALSE()),"") -> Flexible + Social
B25: 15 | C25: 46146 | D25: Pengeluaran | E25: 380000 | F25: Skin care-beauty | G25: Wants | H25: Yes | I25: Stressed | J25: Last lift | K25: =IFERROR(VLOOKUP(F25,Kategori_Mapping!$A:$B,2,FALSE()),"") -> Flexible + Social
B26: 16 | C26: 46146 | D26: Pengeluaran | E26: 25500 | F26: Grab/maxime | G26: Need | H26: No | I26: Neutral | J26: BW ke kos | K26: =IFERROR(VLOOKUP(F26,Kategori_Mapping!$A:$B,2,FALSE()),"") -> Essential Living
B27: 17 | C27: 46146 | D27: Pengeluaran | E27: 102000 | F27: Dipinjam | G27: Need | H27: No | I27: Neutral | J27: Muen | K27: =IFERROR(VLOOKUP(F27,Kategori_Mapping!$A:$B,2,FALSE()),"") -> Transfer (Excluded)
B28: 18 | C28: 46146 | D28: Pemasukan | E28: 3550000 | F28: Muen | J28: Muen bayar hutang | K28: =IFERROR(VLOOKUP(F28,Kategori_Mapping!$A:$B,2,FALSE()),"") -> Income
B29: 19 | C29: 46147 | D29: Pengeluaran | E29: 44700 | F29: Grab/maxime | G29: Need | H29: No | I29: Neutral | J29: Ke TM cangguh | K29: =IFERROR(VLOOKUP(F29,Kategori_Mapping!$A:$B,2,FALSE()),"") -> Essential Living
B30: 20 | C30: 46147 | D30: Pengeluaran | E30: 162314 | F30: YFD | G30: Need | H30: No | I30: Neutral | J30: Fund Adds FB | K30: =IFERROR(VLOOKUP(F30,Kategori_Mapping!$A:$B,2,FALSE()),"") -> Future Building
B31: 21 | C31: 46147 | D31: Pengeluaran | E31: 30000 | F31: Makanan | G31: Need | H31: No | I31: Happy | J31: Makan malam jaga canggu | K31: =IFERROR(VLOOKUP(F31,Kategori_Mapping!$A:$B,2,FALSE()),"") -> Essential Living
B32: 22 | C32: 46147 | D32: Pengeluaran | E32: 46000 | F32: Makanan | G32: Need | H32: Yes | I32: Sad | J32: Makan pagi Korner | K32: =IFERROR(VLOOKUP(F32,Kategori_Mapping!$A:$B,2,FALSE()),"") -> Essential Living
B33: 23 | C33: 46147 | D33: Pemasukan | E33: 11349000 | F33: Gaji | J33: Gaji TM April 2026 | K33: =IFERROR(VLOOKUP(F33,Kategori_Mapping!$A:$B,2,FALSE()),"") -> Income
B34: 24 | C34: 46147 | D34: Pengeluaran | E34: 65920 | F34: Skin care-beauty | G34: Wants | H34: Yes | I34: Stressed | J34: Glimme exfoliating | K34: =IFERROR(VLOOKUP(F34,Kategori_Mapping!$A:$B,2,FALSE()),"") -> Flexible + Social
B35: 25 | C35: 46148 | D35: Pengeluaran | E35: 39700 | F35: Grab/maxime | G35: Need | H35: No | I35: Neutral | J35: TM canggu ke kos | K35: =IFERROR(VLOOKUP(F35,Kategori_Mapping!$A:$B,2,FALSE()),"") -> Essential Living
B36: 26 | C36: 46148 | D36: Pengeluaran | E36: 31000 | F36: Skin care-beauty | G36: Need | H36: Yes | I36: Neutral | J36: shampo | K36: =IFERROR(VLOOKUP(F36,Kategori_Mapping!$A:$B,2,FALSE()),"") -> Flexible + Social
B37: 27 | C37: 46148 | D37: Pengeluaran | E37: 18000 | F37: Makanan | G37: Wants | H37: Yes | I37: Tired | J37: Kopi st regist | K37: =IFERROR(VLOOKUP(F37,Kategori_Mapping!$A:$B,2,FALSE()),"") -> Essential Living
B38: 28 | C38: 46148 | D38: Pengeluaran | E38: 13000 | F38: Makanan | G38: Wants | H38: Yes | I38: Tired | J38: Kue manco | K38: =IFERROR(VLOOKUP(F38,Kategori_Mapping!$A:$B,2,FALSE()),"") -> Essential Living
B39: 29 | C39: 46148 | D39: Pengeluaran | E39: 54200 | F39: Grab/maxime | G39: Need | H39: No | I39: Neutral | J39: Kos ke St regist | K39: =IFERROR(VLOOKUP(F39,Kategori_Mapping!$A:$B,2,FALSE()),"") -> Essential Living
B40: 30 | C40: 46148 | D40: Pengeluaran | E40: 408000 | F40: Asuransi | G40: Need | H40: No | I40: Neutral | J40: IP ay | K40: =IFERROR(VLOOKUP(F40,Kategori_Mapping!$A:$B,2,FALSE()),"") -> Protection
B41: 31 | C41: 46148 | D41: Pengeluaran | E41: 150000 | F41: Asuransi | G41: Need | H41: No | I41: Neutral | J41: bpjs kesehatan Mei | K41: =IFERROR(VLOOKUP(F41,Kategori_Mapping!$A:$B,2,FALSE()),"") -> Protection
B42: 32 | C42: 46148 | D42: Pemasukan | E42: 426000 | F42: Dividen | J42: SIDO | K42: =IFERROR(VLOOKUP(F42,Kategori_Mapping!$A:$B,2,FALSE()),"") -> Income
B43: 33 | C43: 46150 | D43: Pengeluaran | E43: 42000 | F43: Grab/maxime | G43: Need | H43: No | I43: Neutral | J43: ST regis ke kos | K43: =IFERROR(VLOOKUP(F43,Kategori_Mapping!$A:$B,2,FALSE()),"") -> Essential Living
B44: 34 | C44: 46150 | D44: Pengeluaran | E44: 7000 | F44: Grab/maxime | G44: Wants | H44: Yes | I44: Tired | J44: Grab ke londry | K44: =IFERROR(VLOOKUP(F44,Kategori_Mapping!$A:$B,2,FALSE()),"") -> Essential Living
B45: 35 | C45: 46150 | D45: Pengeluaran | E45: 25000 | F45: Makanan | G45: Need | H45: No | I45: Happy | J45: Naspad | K45: =IFERROR(VLOOKUP(F45,Kategori_Mapping!$A:$B,2,FALSE()),"") -> Essential Living
B46: 36 | C46: 46150 | D46: Pengeluaran | E46: 56000 | F46: Pakaian | G46: Need | H46: No | I46: Neutral | J46: Laundry baju selimut | K46: =IFERROR(VLOOKUP(F46,Kategori_Mapping!$A:$B,2,FALSE()),"") -> Flexible + Social
B47: 37 | C47: 46150 | D47: Pengeluaran | E47: 38200 | F47: Grab/maxime | G47: Need | H47: No | I47: Neutral | J47: Kos ke TM Canggu | K47: =IFERROR(VLOOKUP(F47,Kategori_Mapping!$A:$B,2,FALSE()),"") -> Essential Living
B48: 38 | C48: 46150 | D48: Pengeluaran | E48: 25000 | F48: Makanan | G48: Need | H48: No | I48: Happy | J48: Nasi lalapan ayam | K48: =IFERROR(VLOOKUP(F48,Kategori_Mapping!$A:$B,2,FALSE()),"") -> Essential Living
B49: 39 | C49: 46150 | D49: Pemasukan | E49: 1964500 | F49: Dividen | J49: BBRI | K49: =IFERROR(VLOOKUP(F49,Kategori_Mapping!$A:$B,2,FALSE()),"") -> Income
B50: 40 | C50: 46150 | D50: Pengeluaran | E50: 80900 | F50: Skin care-beauty | G50: Need | H50: No | I50: Stressed | J50: Body care | K50: =IFERROR(VLOOKUP(F50,Kategori_Mapping!$A:$B,2,FALSE()),"") -> Flexible + Social
B51: 41 | C51: 46151 | D51: Pengeluaran | E51: 72200 | F51: Grab/maxime | G51: Need | H51: No | I51: Neutral | J51: TM canggu ke westin | K51: =IFERROR(VLOOKUP(F51,Kategori_Mapping!$A:$B,2,FALSE()),"") -> Essential Living
B52: 42 | C52: 46151 | D52: Pengeluaran | E52: 10000 | F52: Sosial | G52: Need | H52: No | I52: Happy | J52: Tip grab | K52: =IFERROR(VLOOKUP(F52,Kategori_Mapping!$A:$B,2,FALSE()),"") -> Flexible + Social
B53: 43 | C53: 46152 | D53: Pengeluaran | E53: 57932 | F53: Skin care-beauty | G53: Wants | H53: No | I53: Stressed | J53: Krim penghilang bulu | K53: =IFERROR(VLOOKUP(F53,Kategori_Mapping!$A:$B,2,FALSE()),"") -> Flexible + Social
B54: 44 | C54: 46152 | D54: Pengeluaran | E54: 15000 | F54: Makanan | G54: Wants | H54: Yes | I54: Tired | J54: Jajan laguna | K54: =IFERROR(VLOOKUP(F54,Kategori_Mapping!$A:$B,2,FALSE()),"") -> Essential Living
B55: 45 | C55: 46153 | D55: Pengeluaran | E55: 4000000 | F55: INVESTASI | G55: Need | H55: No | I55: Angry | J55: Avg down BBCA | K55: =IFERROR(VLOOKUP(F55,Kategori_Mapping!$A:$B,2,FALSE()),"") -> Future Building
B56: 46 | C56: 46153 | D56: Pengeluaran | E56: 2390000 | F56: INVESTASI | G56: Need | H56: No | I56: Angry | J56: Avg down BBRI | K56: =IFERROR(VLOOKUP(F56,Kategori_Mapping!$A:$B,2,FALSE()),"") -> Future Building
B57: 47 | C57: 46153 | D57: Pengeluaran | E57: 12000 | F57: Skin care-beauty | G57: Need | H57: No | I57: Neutral | J57: Softex | K57: =IFERROR(VLOOKUP(F57,Kategori_Mapping!$A:$B,2,FALSE()),"") -> Flexible + Social
B58: 48 | C58: 46153 | D58: Pengeluaran | E58: 38000 | F58: Makanan | G58: Wants | H58: Yes | I58: Happy | J58: Makan jajan air | K58: =IFERROR(VLOOKUP(F58,Kategori_Mapping!$A:$B,2,FALSE()),"") -> Essential Living
B59: 49 | C59: 46153 | D59: Pengeluaran | E59: 41500 | F59: Grab/maxime | G59: Need | H59: No | I59: Neutral | J59: Laguna ke kos | K59: =IFERROR(VLOOKUP(F59,Kategori_Mapping!$A:$B,2,FALSE()),"") -> Essential Living
B60: 50 | C60: 46154 | D60: Pengeluaran | E60: 31200 | F60: Grab/maxime | G60: Need | H60: No | I60: Neutral | J60: Kos ke The meru | K60: =IFERROR(VLOOKUP(F60,Kategori_Mapping!$A:$B,2,FALSE()),"") -> Essential Living
B61: 51 | C61: 46154 | D61: Pengeluaran | E61: 15000 | F61: Makanan | G61: Wants | H61: Yes | I61: Tired | J61: Kopi the meru | K61: =IFERROR(VLOOKUP(F61,Kategori_Mapping!$A:$B,2,FALSE()),"") -> Essential Living
B62: 52 | C62: 46154 | D62: Pengeluaran | E62: 30700 | F62: Grab/maxime | G62: Need | H62: No | I62: Neutral | J62: The meru ke kos | K62: =IFERROR(VLOOKUP(F62,Kategori_Mapping!$A:$B,2,FALSE()),"") -> Essential Living
B63: 53 | C63: 46155 | D63: Pemasukan | E63: 29990 | F63: Lain-lain | J63: Tiktok Live😱 | K63: =IFERROR(VLOOKUP(F63,Kategori_Mapping!$A:$B,2,FALSE()),"") -> Income
B64: 54 | C64: 46155 | D64: Pengeluaran | E64: 67000 | F64: Pakaian | G64: Need | H64: No | I64: Happy | J64: Bridesmide egy | K64: =IFERROR(VLOOKUP(F64,Kategori_Mapping!$A:$B,2,FALSE()),"") -> Flexible + Social
B65: 55 | C65: 46155 | D65: Pengeluaran | E65: 26700 | F65: Grab/maxime | G65: Need | H65: No | I65: Neutral | J65: Kos ke TM seminyak | K65: =IFERROR(VLOOKUP(F65,Kategori_Mapping!$A:$B,2,FALSE()),"") -> Essential Living
B66: 56 | C66: 46155 | D66: Pengeluaran | E66: 15000 | F66: Makanan | G66: Need | H66: No | I66: Neutral | J66: Makan brunch | K66: =IFERROR(VLOOKUP(F66,Kategori_Mapping!$A:$B,2,FALSE()),"") -> Essential Living
B67: 57 | C67: 46155 | D67: Pengeluaran | E67: 20000 | F67: Makanan | G67: Need | H67: No | I67: Happy | J67: Lalapan lele | K67: =IFERROR(VLOOKUP(F67,Kategori_Mapping!$A:$B,2,FALSE()),"") -> Essential Living
B68: 58 | C68: 46156 | D68: Pengeluaran | E68: 95800 | F68: Skin care-beauty | G68: Wants | H68: Yes | I68: Stressed | J68: Lavojoi body serum | K68: =IFERROR(VLOOKUP(F68,Kategori_Mapping!$A:$B,2,FALSE()),"") -> Flexible + Social
B69: 59 | C69: 46156 | D69: Pengeluaran | E69: 370000 | F69: Skin care-beauty | G69: Need | H69: No | I69: Happy | J69: Treatment (massage, scrub, mnicure, pedicure, potong rambut, masker rambut) | K69: =IFERROR(VLOOKUP(F69,Kategori_Mapping!$A:$B,2,FALSE()),"") -> Flexible + Social
B70: 60 | C70: 46156 | D70: Pengeluaran | E70: 200000 | F70: Sosial | G70: Wants | H70: Yes | I70: Happy | J70: Tip treatment niki salon | K70: =IFERROR(VLOOKUP(F70,Kategori_Mapping!$A:$B,2,FALSE()),"") -> Flexible + Social
B71: 61 | C71: 46156 | D71: Pengeluaran | E71: 23200 | F71: Grab/maxime | G71: Need | H71: No | I71: Neutral | J71: TM seminyak ke kos | K71: =IFERROR(VLOOKUP(F71,Kategori_Mapping!$A:$B,2,FALSE()),"") -> Essential Living
B72: 62 | C72: 46156 | D72: Pengeluaran | E72: 27700 | F72: Grab/maxime | G72: Need | H72: No | I72: Neutral | J72: Kos ke GKI | K72: =IFERROR(VLOOKUP(F72,Kategori_Mapping!$A:$B,2,FALSE()),"") -> Essential Living
B73: 63 | C73: 46156 | D73: Pengeluaran | E73: 50000 | F73: Persembahan | G73: Need | H73: No | I73: Neutral | J73: Ibadah kenaikan | K73: =IFERROR(VLOOKUP(F73,Kategori_Mapping!$A:$B,2,FALSE()),"") -> Flexible + Social
B74: 64 | C74: 46156 | D74: Pengeluaran | E74: 50000 | F74: Makanan | G74: Need | H74: Yes | I74: Neutral | J74: Richesee factory | K74: =IFERROR(VLOOKUP(F74,Kategori_Mapping!$A:$B,2,FALSE()),"") -> Essential Living
B75: 65 | C75: 46156 | D75: Pengeluaran | E75: 25000 | F75: Makanan | G75: Need | H75: No | I75: Happy | J75: seblak | K75: =IFERROR(VLOOKUP(F75,Kategori_Mapping!$A:$B,2,FALSE()),"") -> Essential Living
... B81: 71 | C81: 46157 | D81: Pengeluaran | E81: 15000 | F81: Makanan | G81: Wants | H81: Yes | I81: Happy | J81: batagor tahu | K81: =IFERROR(VLOOKUP(F81,Kategori_Mapping!$A:$B,2,FALSE()),"") -> Essential Living
B82: 72 | C82: 46157 | D82: Pemasukan | E82: 200000 | F82: Lain-lain | J82: Tip dri pasien | K82: =IFERROR(VLOOKUP(F82,Kategori_Mapping!$A:$B,2,FALSE()),"") -> Income
B83: 73 | C83: 46158 | D83: Pengeluaran | E83: 16000 | F83: Grab/maxime | G83: Need | H83: No | I83: Neutral | J83: Subs Grab | K83: =IFERROR(VLOOKUP(F83,Kategori_Mapping!$A:$B,2,FALSE()),"") -> Essential Living
B84: 74 | C84: 46158 | D84: Pengeluaran | E84: 71000 | F84: Grab/maxime | G84: Need | H84: No | I84: Neutral | J84: TM canggu ke Laguna | K84: =IFERROR(VLOOKUP(F84,Kategori_Mapping!$A:$B,2,FALSE()),"") -> Essential Living
B85: 75 | C85: 46158 | D85: Pengeluaran | E85: 50000 | F85: Sosial | G85: Wants | H85: Yes | I85: Happy | J85: Tip grab | K85: =IFERROR(VLOOKUP(F85,Kategori_Mapping!$A:$B,2,FALSE()),"") -> Flexible + Social
B86: 76 | C86: 46158 | D86: Pengeluaran | E86: 300000 | F86: Sosial | G86: Need | H86: No | I86: Neutral | J86: Lale | K86: =IFERROR(VLOOKUP(F86,Kategori_Mapping!$A:$B,2,FALSE()),"") -> Flexible + Social
B87: 77 | C87: 46159 | D87: Pengeluaran | E87: 110000 | F87: Subscription | G87: Need | H87: No | I87: Neutral | J87: IG centang | K87: =IFERROR(VLOOKUP(F87,Kategori_Mapping!$A:$B,2,FALSE()),"") -> Flexible + Social
B88: 78 | C88: 46159 | D88: Pengeluaran | E88: 157989 | F88: Pakaian | G88: Need | H88: Yes | I88: Happy | J88: Bra off shoulders | K88: =IFERROR(VLOOKUP(F88,Kategori_Mapping!$A:$B,2,FALSE()),"") -> Flexible + Social
B89: 79 | C89: 46161 | D89: Pengeluaran | E89: 43700 | F89: Grab/maxime | G89: Need | H89: No | I89: Neutral | J89: WS ke kos | K89: =IFERROR(VLOOKUP(F89,Kategori_Mapping!$A:$B,2,FALSE()),"") -> Essential Living
B90: 80 | C90: 46161 | D90: Pengeluaran | E90: 30000 | F90: Makanan | G90: Need | H90: No | I90: Happy | J90: Naspad | K90: =IFERROR(VLOOKUP(F90,Kategori_Mapping!$A:$B,2,FALSE()),"") -> Essential Living
B91: 81 | C91: 46161 | D91: Pengeluaran | E91: 23000 | F91: Pakaian | G91: Need | H91: No | I91: Neutral | J91: Laundry | K91: =IFERROR(VLOOKUP(F91,Kategori_Mapping!$A:$B,2,FALSE()),"") -> Flexible + Social
B92: 82 | C92: 46161 | D92: Pengeluaran | E92: 250000 | F92: Sosial | G92: Wants | H92: Yes | I92: Happy | J92: Yankes diamed | K92: =IFERROR(VLOOKUP(F92,Kategori_Mapping!$A:$B,2,FALSE()),"") -> Flexible + Social
B93: 83 | C93: 46162 | D93: Pengeluaran | E93: 41200 | F93: Grab/maxime | G93: Need | H93: No | I93: Neutral | J93: Kos ke TM Canggu | K93: =IFERROR(VLOOKUP(F93,Kategori_Mapping!$A:$B,2,FALSE()),"") -> Essential Living
B94: 84 | C94: 46162 | D94: Pengeluaran | E94: 35000 | F94: Makanan | G94: Need | H94: No | I94: Neutral | J94: Makan sehari | K94: =IFERROR(VLOOKUP(F94,Kategori_Mapping!$A:$B,2,FALSE()),"") -> Essential Living
... B100: 90 | C100: 46163 | D100: Pengeluaran | E100: 52200 | F100: Grab/maxime | G100: Need | H100: No | I100: Neutral | J100: TM canggu ke The Meru sanur | K100: =IFERROR(VLOOKUP(F100,Kategori_Mapping!$A:$B,2,FALSE()),"") -> Essential Living
B101: 91 | C101: 46163 | D101: Pemasukan | E101: 27853 | F101: Lain-lain | J101: Tiktok Live😱 | K101: =IFERROR(VLOOKUP(F101,Kategori_Mapping!$A:$B,2,FALSE()),"") -> Income
B102: 92 | C102: 46163 | D102: Pemasukan | E102: 5655655 | F102: Gaji | J102: OC be health april | K102: =IFERROR(VLOOKUP(F102,Kategori_Mapping!$A:$B,2,FALSE()),"") -> Income
B103: 93 | C103: 46163 | D103: Pengeluaran | E103: 502500 | F103: Pakaian | G103: Wants | H103: Yes | I103: Happy | J103: jahit baju | K103: =IFERROR(VLOOKUP(F103,Kategori_Mapping!$A:$B,2,FALSE()),"") -> Flexible + Social
B104: 94 | C104: 46163 | D104: Pengeluaran | E104: 3601629 | F104: Tagihan | G104: Need | H104: No | I104: Sad | J104: CC april + muen | K104: =IFERROR(VLOOKUP(F104,Kategori_Mapping!$A:$B,2,FALSE()),"") -> Essential Living
B105: 95 | C105: 46164 | D105: Pengeluaran | E105: 36850 | F105: Makanan | G105: Need | H105: No | I105: Happy | J105: Makan sehari | K105: =IFERROR(VLOOKUP(F105,Kategori_Mapping!$A:$B,2,FALSE()),"") -> Essential Living
B106: 96 | C106: 46164 | D106: Pengeluaran | E106: 152656 | F106: Pakaian | G106: Wants | H106: Yes | I106: Stressed | J106: Heels | K106: =IFERROR(VLOOKUP(F106,Kategori_Mapping!$A:$B,2,FALSE()),"") -> Flexible + Social
B107: 97 | C107: 46165 | D107: Pengeluaran | E107: 365000 | F107: Sosial | G107: Wants | H107: No | I107: Happy | J107: Kado egy | K107: =IFERROR(VLOOKUP(F107,Kategori_Mapping!$A:$B,2,FALSE()),"") -> Flexible + Social
B108: 98 | C108: 46165 | D108: Pengeluaran | E108: 45700 | F108: Grab/maxime | G108: Need | H108: No | I108: Neutral | J108: TM seminyak ke HR | K108: =IFERROR(VLOOKUP(F108,Kategori_Mapping!$A:$B,2,FALSE()),"") -> Essential Living
B109: 99 | C109: 46165 | D109: Pengeluaran | E109: 87840 | F109: Makanan | G109: Wants | H109: Yes | I109: Tired | J109: Soesweet bali | K109: =IFERROR(VLOOKUP(F109,Kategori_Mapping!$A:$B,2,FALSE()),"") -> Essential Living
B110: 100 | C110: 46166 | D110: Pengeluaran | E110: 101500 | F110: Pulsa | G110: Need | H110: No | I110: Neutral | J110: Pulsa data ayuti IP | K110: =IFERROR(VLOOKUP(F110,Kategori_Mapping!$A:$B,2,FALSE()),"") -> Essential Living
B111: 101 | C111: 46167 | D111: Pengeluaran | E111: 43200 | F111: Grab/maxime | G111: Need | H111: No | I111: Neutral | J111: HR ke TM smyk | K111: =IFERROR(VLOOKUP(F111,Kategori_Mapping!$A:$B,2,FALSE()),"") -> Essential Living
B112: 102 | C112: 46167 | D112: Pengeluaran | E112: 26000 | F112: Makanan | G112: Wants | H112: Yes | I112: Tired | J112: Jajan | K112: =IFERROR(VLOOKUP(F112,Kategori_Mapping!$A:$B,2,FALSE()),"") -> Essential Living
B113: 103 | C113: 46167 | D113: Pengeluaran | E113: 135000 | F113: Makanan | G113: Need | H113: Yes | I113: Happy | J113: Sam sam merekak | K113: =IFERROR(VLOOKUP(F113,Kategori_Mapping!$A:$B,2,FALSE()),"") -> Essential Living
B114: 104 | C114: 46168 | D114: Pengeluaran | E114: 1849485 | F114: Transportasi | G114: Need | H114: No | I114: Neutral | J114: Pesawat dps ke mks | K114: =IFERROR(VLOOKUP(F114,Kategori_Mapping!$A:$B,2,FALSE()),"") -> Essential Living
... B141: 131 | C141: 46173 | D141: Pengeluaran | E141: 21000 | F141: Admin bank | G141: Need | H141: No | I141: Neutral | J141: Admin Bank | K141: =IFERROR(VLOOKUP(F141,Kategori_Mapping!$A:$B,2,FALSE()),"") -> Essential Living

Sheet Baseline
B1: YFD BASELINE — Financial Health Check-Up & FTSA-32
B2: Diisi / diperbarui setiap 6 bulan. Sumber data untuk Sheet 2 (Financial Health Dashboard) dan Sheet 3 (Behavioral Dashboard).
B4: A. IDENTITY & FINANCIAL STAGE
B5: Last Check-up | C5: 46113
B6: Next Review (auto, +6 bulan) | C6: =IF(C5="","",EDATE(C5,6)) -> 46296
B7: Current Goal | C7: (isi tujuan keuangan saat ini — belum diisi user)
B9: B. FINANCIAL STAGE SCORING (Knowing Your Financial Stage — 18 Pertanyaan)
B10: Catatan: skor mentah per pertanyaan belum tersedia dari user (baru hasil akhir). Field "Skor Manual" di bawah dipakai sebagai sumber utama saat ini.
B12: No | C12: Pertanyaan (ringkas) | D12: Skor (0-4, isi manual / dari bot)
B13: 1 | C13: Tanggungan selain diri sendiri
B14: 2 | C14: Rata-rata pendapatan/bulan
B15: 3 | C15: Pengeluaran vs pemasukan
B16: 4 | C16: Frekuensi cashflow negatif
B17: 5 | C17: Dana darurat
B18: 6 | C18: Hutang konsumtif
B19: 7 | C19: Proteksi kesehatan
B20: 8 | C20: Asuransi jiwa
B21: 9 | C21: Income protection / kondisi kritis
B22: 10 | C22: Tabungan/aset kelola (di luar emergency fund)
B23: 11 | C23: Investasi/tabungan hari tua
B24: 12 | C24: Investasi high risk
... B27: 15 | C27: Warisan finansial
C28: TOTAL SKOR RAW (auto, dari 15-item di atas) | D28: =SUM(D13:D27) -> 0 | F28: Skor Manual Override | G28: 30 | H28: Hasil check-up klinik: total 30 (raw 15-item belum diisi)
C29: Stage berdasarkan Total Skor (auto: pakai raw>0, kalau tidak manual) | D29: =IF(D28>0,IF(D28<=12,"Surviving",IF(D28<=22,"Growing",IF(D28<=33,"Steady","Comfortable"))),IF(G28>0,IF(G28<=12,"Surviving",IF(G28<=22,"Growing",IF(G28<=33,"Steady","Comfortable"))),"")) -> Steady
C30: FINANCIAL STAGE — FINAL (manual override, mis. dari hasil check-up klinik) | D30: Steady | E30: ← Sel ini yang dipakai semua dashboard.
B32: C. BASELINE FINANCIAL DATA
B33: Average Monthly Income | D33: 20000000
B34: Emergency Fund (kondisi) | D34: 3-5x pengeluaran bulanan
B35: Tabungan Non-Emergency | D35: 0 | E35: (belum diisi user — default 0)
B37: Total Asset — Rincian
C38: Tanah | D38: 100000000
C39: Emas | D39: 10000000
C40: Saham | D40: 1000000
C41: TOTAL ASSET (auto) | D41: =SUM(D38:D40) -> 111000000
B42: Total Investment (aset likuid produktif) | D42: =D40 -> 1000000 | E42: (= Saham. Emas & Tanah diperlakukan sbg aset, bukan investasi likuid.)
B43: Total Debt | D43: 0 | E43: Dikonfirmasi user: tidak punya hutang. Total Debt = 0 (valid, bukan asumsi).
B45: D. PROTECTION
B46: Item | C46: Satuan | D46: Nominal | E46: x | F46: Setahun (auto)
B47: BPJS Kesehatan | C47: /bulan | D47: 150000 | E47: 12 | F47: =D47*E47 -> 1800000
B48: Unit Link (top up) | C48: /tahun | D48: 2000000 | E48: 1 | F48: =D48*E48 -> 2000000
B49: Income Protection | C49: /bulan | D49: 408000 | E49: 12 | F49: =D49*E49 -> 4896000
B50: Asuransi Jiwa | C50: /tahun | D50: 6665000 | E50: 1 | F50: =D50*E50 -> 6665000
B51: TOTAL PROTECTION / TAHUN (auto) | F51: =SUM(F47:F50) -> 15361000
B52: TOTAL PROTECTION / BULAN (auto, setara) | F52: =F51/12 -> 1280083.3
B54: E. FTSA-32 — FINANCIAL TRAUMA SELF ASSESSMENT
B55: Skala 1-5 (1=Sangat Tidak Sesuai ... 5=Sangat Sesuai). Isi 32 item via bot/klinik. Jika belum tersedia, gunakan "Skor Manual Override" di akhir tiap domain.
B57: CHD — Control & Hypervigilance Dysregulation (The Controller)
B58: Cemas jika tidak tahu detail kondisi keuangan
B59: Sulit mempercayakan keuangan ke orang lain
B60: Tidak aman tanpa kontrol penuh atas pengeluaran
B61: Sering memikirkan skenario keuangan terburuk
B62: Pengeluaran tak terduga = kehilangan kendali
B63: Memantau saldo/investasi berlebihan
B64: Sulit menikmati uang karena takut kehabisan
B65: Keamanan finansial = kontrol total
B66: TOTAL CHD (auto, dari 32-item) | D66: =SUM(D58:D65) -> 0
B67: Skor Manual Override CHD (isi jika 8-item blm tersedia) | D67: 32 | E67: Hasil baseline klinik: CHD = 32.
B68: TOTAL CHD — FINAL (auto: pakai raw kalau ada, kalau tidak pakai manual) | D68: =IF(D66>0,D66,D67) -> 32
B69: Severity CHD (auto) | D69: =IF(D68="","",IF(D68<=16,"Regulasi Stabil",IF(D68<=24,"Mild Dysregulation",IF(D68<=32,"Moderate Dysregulation","Severe Dysregulation")))) -> Moderate Dysregulation
B71: RVD — Risk & Volatility Avoidance Dysregulation (The Avoider)
B72: Menunda keputusan keuangan penting
B73: Menghindari melihat laporan keuangan
B74: Takut berinvestasi karena risiko
B75: Menyimpan uang tanpa strategi jangka panjang
B76: Ketidakpastian ekonomi membuat lumpuh
B77: Lebih memilih tidak tahu daripada hadapi kerugian
B78: Menunda diskusi finansial karena tidak nyaman
B79: Stres hanya dengan membicarakan uang
B80: TOTAL RVD (auto, dari 32-item) | D80: =SUM(D72:D79) -> 0
B81: Skor Manual Override RVD (isi jika 8-item blm tersedia) | D81: 16 | E81: Hasil baseline klinik: RVD = 16 (Regulasi Stabil, 8-16).
B82: TOTAL RVD — FINAL (auto: pakai raw kalau ada, kalau tidak pakai manual) | D82: =IF(D80>0,D80,D81) -> 16
B83: Severity RVD (auto) | D83: =IF(D82="","",IF(D82<=16,"Regulasi Stabil",IF(D82<=24,"Mild Dysregulation",IF(D82<=32,"Moderate Dysregulation","Severe Dysregulation")))) -> Regulasi Stabil
B85: SSD — Scarcity-Driven Safety Dysregulation (The Overworker)
B86: Harus terus bekerja agar merasa aman
B87: Sulit berhenti meski sudah cukup
B88: Nilai diri dikaitkan dengan produktivitas/penghasilan
B89: Merasa bersalah jika tidak menghasilkan uang
B90: Istirahat membuat tidak aman
B91: Takut kehilangan status/standar hidup
B92: Cemas jika tidak ada pemasukan aktif
B93: Keamanan hanya dari kerja keras tanpa henti
B94: TOTAL SSD (auto, dari 32-item) | D94: =SUM(D86:D93) -> 0
B95: Skor Manual Override SSD (isi jika 8-item blm tersedia) | D95: 40 | E95: Hasil baseline klinik: SSD = 40.
B96: TOTAL SSD — FINAL (auto: pakai raw kalau ada, kalau tidak pakai manual) | D96: =IF(D94>0,D94,D95) -> 40
B97: Severity SSD (auto) | D97: =IF(D96="","",IF(D96<=16,"Regulasi Stabil",IF(D96<=24,"Mild Dysregulation",IF(D96<=32,"Moderate Dysregulation","Severe Dysregulation")))) -> Severe Dysregulation
B99: ESD — Emotional Spending Dysregulation (The Impulsive)
B100: Belanja untuk memperbaiki suasana hati
B101: Menyesal setelah pembelian emosional
B102: Sulit menahan dorongan membeli
B103: Uang sebagai penghargaan diri sendiri
B104: Mengambil keputusan finansial saat emosi kuat
B105: Euforia saat belanja lalu rasa bersalah
B106: Sulit bedakan kebutuhan/keinginan saat stres
B107: Pengeluaran meningkat saat tidak stabil emosi
B108: TOTAL ESD (auto, dari 32-item) | D108: =SUM(D100:D107) -> 0
B109: Skor Manual Override ESD (isi jika 8-item blm tersedia) | D109: 24 | E109: Hasil baseline klinik: ESD = 24 (Mild Dysregulation, 17-24).
B110: TOTAL ESD — FINAL (auto: pakai raw kalau ada, kalau tidak pakai manual) | D110: =IF(D108>0,D108,D109) -> 24
B111: Severity ESD (auto) | D111: =IF(D110="","",IF(D110<=16,"Regulasi Stabil",IF(D110<=24,"Mild Dysregulation",IF(D110<=32,"Moderate Dysregulation","Severe Dysregulation")))) -> Mild Dysregulation
B113: F. FTSA-32 PROFILE SUMMARY (auto)
B114: Domain | C114: Skor Final | D114: Severity | E114: Assessed? | F114: (helper, tie-break)
...

Sheet Financial Health Dashboard
B1: YFD FIRST AID — FINANCIAL HEALTH DASHBOARD | F1: Filter Periode (bulan): | G1: 3 | M1: (helper: semua kategori & total - jangan hapus) | O1: tie-break
B2: Ringkasan kondisi keuangan periode berjalan | M2: Admin bank | N2: =SUMIFS(Input!$E:$E,Input!$D:$D,"Pengeluaran",Input!$F:$F,M2,Input!$C:$C,">="&$E$3,Input!$C:$C,"<="&$C$3) -> 59500 | O2: =N2+ROW()*0.0000001 -> 59500
B3: MaxDate (auto) | C3: =MAX(Input!C:C) -> 46173 | D3: StartDate (auto) | E3: =EDATE(DATE(YEAR(C3),MONTH(C3),1),-(G1-1)) -> 46082 | M3: YFD | N3: =SUMIFS(Input!$E:$E,Input!$D:$D,"Pengeluaran",Input!$F:$F,M3,Input!$C:$C,">="&$E$3,Input!$C:$C,"<="&$C$3) -> 309314 | O3: =N3+ROW()*0.0000001 -> 309314
M4: Sosial | N4: =SUMIFS(Input!$E:$E,Input!$D:$D,"Pengeluaran",Input!$F:$F,M4,Input!$C:$C,">="&$E$3,Input!$C:$C,"<="&$C$3) -> 3377085 | O4: =N4+ROW()*0.0000001 -> 3377085
B5: CLINICAL SUMMARY | M5: Grab/maxime | N5: =SUMIFS(Input!$E:$E,Input!$D:$D,"Pengeluaran",Input!$F:$F,M5,Input!$C:$C,">="&$E$3,Input!$C:$C,"<="&$C$3) -> 1220900 | O5: =N5+ROW()*0.0000001 -> 1220900
B6: Financial Stage | D6: Last Check-up | F6: Next Review | H6: Current Goal | M6: Skin care-beauty | N6: =SUMIFS(Input!$E:$E,Input!$D:$D,"Pengeluaran",Input!$F:$F,M6,Input!$C:$C,">="&$E$3,Input!$C:$C,"<="&$C$3) -> 1340989 | O6: =N6+ROW()*0.0000001 -> 1340989
B7: =Baseline!D30 -> Steady | D7: =Baseline!C5 -> 46113 | F7: =Baseline!C6 -> 46296 | H7: =Baseline!D8 -> 0 | M7: Networking | N7: =SUMIFS(Input!$E:$E,Input!$D:$D,"Pengeluaran",Input!$F:$F,M7,Input!$C:$C,">="&$E$3,Input!$C:$C,"<="&$C$3) -> 77000 | O7: =N7+ROW()*0.0000001 -> 77000
M8: Hiburan | N8: =SUMIFS(Input!$E:$E,Input!$D:$D,"Pengeluaran",Input!$F:$F,M8,Input!$C:$C,">="&$E$3,Input!$C:$C,"<="&$C$3) -> 174000 | O8: =N8+ROW()*0.0000001 -> 174000
B9: FINANCIAL VITAL SIGN | M9: Makanan | N9: =SUMIFS(Input!$E:$E,Input!$D:$D,"Pengeluaran",Input!$F:$F,M9,Input!$C:$C,">="&$E$3,Input!$C:$C,"<="&$C$3) -> 1263690 | O9: =N9+ROW()*0.0000001 -> 1263690
B10: TOTAL PENDAPATAN | D10: TOTAL PENGELUARAN | F10: CASHFLOW (SURPLUS) | H10: SAVING RATE | J10: TOTAL TRANSAKSI | M10: Asuransi | N10: =SUMIFS(Input!$E:$E,Input!$D:$D,"Pengeluaran",Input!$F:$F,M10,Input!$C:$C,">="&$E$3,Input!$C:$C,"<="&$C$3) -> 558000 | O10: =N10+ROW()*0.0000001 -> 558000
B11: =SUMIFS(Input!$E:$E,Input!$D:$D,"Pemasukan",Input!$C:$C,">="&$E$3,Input!$C:$C,"<="&$C$3) -> 31124475 | D11: =SUMIFS(Input!$E:$E,Input!$D:$D,"Pengeluaran",Input!$C:$C,">="&$E$3,Input!$C:$C,"<="&$C$3) -> 25295237 | F11: =B11-D11 -> 5829238 | H11: =IF(B11=0,0,F11/B11) -> 0.18728791 | J11: =COUNTIFS(Input!$C:$C,">="&$E$3,Input!$C:$C,"<="&$C$3) -> 131 | M11: Pakaian | N11: =SUMIFS(Input!$E:$E,Input!$D:$D,"Pengeluaran",Input!$F:$F,M11,Input!$C:$C,">="&$E$3,Input!$C:$C,"<="&$C$3) -> 959145 | O11: =N11+ROW()*0.0000001 -> 959145
M12: INVESTASI | N12: =SUMIFS(Input!$E:$E,Input!$D:$D,"Pengeluaran",Input!$F:$F,M12,Input!$C:$C,">="&$E$3,Input!$C:$C,"<="&$C$3) -> 6390000 | O12: =N12+ROW()*0.0000001 -> 6390000
B13: BUDGET PRESCRIPTION (4 Bucket) | M13: Persembahan | N13: =SUMIFS(Input!$E:$E,Input!$D:$D,"Pengeluaran",Input!$F:$F,M13,Input!$C:$C,">="&$E$3,Input!$C:$C,"<="&$C$3) -> 85000 | O13: =N13+ROW()*0.0000001 -> 85000
B14: Kategori | C14: Aktual | D14: % dari Income | E14: Ideal (%) | F14: Selisih | G14: Progress vs Ideal | H14: Status | I14: Tipe Target | M14: Subscription | N14: =SUMIFS(Input!$E:$E,Input!$D:$D,"Pengeluaran",Input!$F:$F,M14,Input!$C:$C,">="&$E$3,Input!$C:$C,"<="&$C$3) -> 110000 | O14: =N14+ROW()*0.0000001 -> 110000
B15: Essential Living | C15: =SUMIFS(Input!$E:$E,Input!$D:$D,"Pengeluaran",Input!$K:$K,B15,Input!$C:$C,">="&$E$3,Input!$C:$C,"<="&$C$3) -> 10562704 | D15: =IF($B$11=0,0,C15/$B$11) -> 0.33936971 | E15: =INDEX(Kategori_Mapping!$H:$K,MATCH(Baseline!$D$30,Kategori_Mapping!$G:$G,0),MATCH(B15,Kategori_Mapping!$H$1:$K$1,0)) -> 0.5 | F15: =D15-E15 -> -0.16063029 | G15: =IF(E15=0,0,D15/E15) -> 0.67873942 | H15: =IF(D15<=E15,"Sehat (dalam batas)","Melebihi batas maksimal — lebih "&TEXT(D15-E15,"0.0%")) -> Sehat (dalam batas) | I15: Maksimal (makin rendah makin sehat) | M15: Rumah | N15: =SUMIFS(Input!$E:$E,Input!$D:$D,"Pengeluaran",Input!$F:$F,M15,Input!$C:$C,">="&$E$3,Input!$C:$C,"<="&$C$3) -> 2116000 | O15: =N15+ROW()*0.0000001 -> 2116000
B16: Future Building | C16: =SUMIFS(Input!$E:$E,Input!$D:$D,"Pengeluaran",Input!$K:$K,B16,Input!$C:$C,">="&$E$3,Input!$C:$C,"<="&$C$3) -> 6776314 | D16: =IF($B$11=0,0,C16/$B$11) -> 0.21771657 | E16: =INDEX(Kategori_Mapping!$H:$K,MATCH(Baseline!$D$30,Kategori_Mapping!$G:$G,0),MATCH(B16,Kategori_Mapping!$H$1:$K$1,0)) -> 0.3 | F16: =D16-E16 -> -0.082283428 | G16: =IF(E16=0,0,D16/E16) -> 0.72572191 | H16: =IF(D16>=E16,"Sehat (memenuhi minimal)","Di bawah minimal — kurang "&TEXT(E16-D16,"0.0%")) -> Di bawah minimal — kurang 8.2% | I16: Minimal (makin tinggi makin sehat) | M16: Tagihan | N16: =SUMIFS(Input!$E:$E,Input!$D:$D,"Pengeluaran",Input!$F:$F,M16,Input!$C:$C,">="&$E$3,Input!$C:$C,"<="&$C$3) -> 3601629 | O16: =N16+ROW()*0.0000001 -> 3601629
B17: Protection | C17: =SUMIFS(Input!$E:$E,Input!$D:$D,"Pengeluaran",Input!$K:$K,B17,Input!$C:$C,">="&$E$3,Input!$C:$C,"<="&$C$3) -> 558000 | D17: =IF($B$11=0,0,C17/$B$11) -> 0.017928013 | E17: =INDEX(Kategori_Mapping!$H:$K,MATCH(Baseline!$D$30,Kategori_Mapping!$G:$G,0),MATCH(B17,Kategori_Mapping!$H$1:$K$1,0)) -> 0.1 | F17: =D17-E17 -> -0.082071987 | G17: =IF(E17=0,0,D17/E17) -> 0.17928013 | H17: =IF(D17<=E17,"Sehat (dalam batas)","Melebihi batas maksimal — lebih "&TEXT(D17-E17,"0.0%")) -> Sehat (dalam batas) | I17: Maksimal (jangan melebihi) | M17: Pulsa | N17: =SUMIFS(Input!$E:$E,Input!$D:$D,"Pengeluaran",Input!$F:$F,M17,Input!$C:$C,">="&$E$3,Input!$C:$C,"<="&$C$3) -> 101500 | O17: =N17+ROW()*0.0000001 -> 101500
B18: Flexible + Social | C18: =SUMIFS(Input!$E:$E,Input!$D:$D,"Pengeluaran",Input!$K:$K,B18,Input!$C:$C,">="&$E$3,Input!$C:$C,"<="&$C$3) -> 7296219 | D18: =IF($B$11=0,0,C18/$B$11) -> 0.23442063 | E18: =INDEX(Kategori_Mapping!$H:$K,MATCH(Baseline!$D$30,Kategori_Mapping!$G:$G,0),MATCH(B18,Kategori_Mapping!$H$1:$K$1,0)) -> 0.1 | F18: =D18-E18 -> 0.13442063 | G18: =IF(E18=0,0,D18/E18) -> 2.3442063 | H18: =IF(D18<=E18,"Sehat (dalam batas)","Melebihi batas maksimal — lebih "&TEXT(D18-E18,"0.0%")) -> Melebihi batas maksimal — lebih 13.4% | I18: Maksimal (jangan melebihi) | M18: Transportasi | N18: =SUMIFS(Input!$E:$E,Input!$D:$D,"Pengeluaran",Input!$F:$F,M18,Input!$C:$C,">="&$E$3,Input!$C:$C,"<="&$C$3) -> 2099485 | O18: =N18+ROW()*0.0000001 -> 2099485
B19: TOTAL | C19: =SUM(C15:C18) -> 25193237 | D19: =SUM(D15:D18) -> 0.80943492 | M19: Mega-kurnia | N19: =SUMIFS(Input!$E:$E,Input!$D:$D,"Pengeluaran",Input!$F:$F,M19,Input!$C:$C,">="&$E$3,Input!$C:$C,"<="&$C$3) -> 1050000 | O19: =N19+ROW()*0.0000001 -> 1050000
B20: EXPENSE ANALYSIS — TOP KATEGORI | G20: FINANCIAL PROGRESS (BULANAN) | M20: Hadiah | N20: =SUMIFS(Input!$E:$E,Input!$D:$D,"Pengeluaran",Input!$F:$F,M20,Input!$C:$C,">="&$E$3,Input!$C:$C,"<="&$C$3) -> 200000 | O20: =N20+ROW()*0.0000001 -> 200000
B21: Kategori | C21: Total | D21: % dari Total | G21: Bulan | H21: Pendapatan | I21: Pengeluaran | J21: Cashflow | M21: Lale | N21: =SUMIFS(Input!$E:$E,Input!$D:$D,"Pengeluaran",Input!$F:$F,M21,Input!$C:$C,">="&$E$3,Input!$C:$C,"<="&$C$3) -> 100000 | O21: =N21+ROW()*0.0000001 -> 100000
B22: =IFERROR(INDEX($M$2:$M$21,MATCH(LARGE($O$2:$O$21,1),$O$2:$O$21,0)),"") -> INVESTASI | C22: =IFERROR(INDEX($N$2:$N$21,MATCH(LARGE($O$2:$O$21,1),$O$2:$O$21,0)),0) -> 6390000 | D22: =IF($D$11=0,0,C22/$D$11) -> 0.25261673 | G22: =EDATE($C$3,-11) -> 45838 | H22: =SUMIFS(Input!$E:$E,Input!$D:$D,"Pemasukan",Input!$C:$C,">="&DATE(YEAR(G22),MONTH(G22),1),Input!$C:$C,"<="&EOMONTH(G22,0)) -> 0 | I22: =SUMIFS(Input!$E:$E,Input!$D:$D,"Pengeluaran",Input!$C:$C,">="&DATE(YEAR(G22),MONTH(G22),1),Input!$C:$C,"<="&EOMONTH(G22,0)) -> 0 | J22: =H22-I22 -> 0
B23: =IFERROR(INDEX($M$2:$M$21,MATCH(LARGE($O$2:$O$21,2),$O$2:$O$21,0)),"") -> Tagihan | C23: =IFERROR(INDEX($N$2:$N$21,MATCH(LARGE($O$2:$O$21,2),$O$2:$O$21,0)),0) -> 3601629 | D23: =IF($D$11=0,0,C23/$D$11) -> 0.14238368 | G23: =EDATE($C$3,-10) -> 45869 | H23: =SUMIFS(Input!$E:$E,Input!$D:$D,"Pemasukan",Input!$C:$C,">="&DATE(YEAR(G23),MONTH(G23),1),Input!$C:$C,"<="&EOMONTH(G23,0)) -> 0 | I23: =SUMIFS(Input!$E:$E,Input!$D:$D,"Pengeluaran",Input!$C:$C,">="&DATE(YEAR(G23),MONTH(G23),1),Input!$C:$C,"<="&EOMONTH(G23,0)) -> 0 | J23: =H23-I23 -> 0
B24: =IFERROR(INDEX($M$2:$M$21,MATCH(LARGE($O$2:$O$21,3),$O$2:$O$21,0)),"") -> Sosial | C24: =IFERROR(INDEX($N$2:$N$21,MATCH(LARGE($O$2:$O$21,3),$O$2:$O$21,0)),0) -> 3377085 | D24: =IF($D$11=0,0,C24/$D$11) -> 0.13350675 | G24: =EDATE($C$3,-9) -> 45900 | H24: =SUMIFS(Input!$E:$E,Input!$D:$D,"Pemasukan",Input!$C:$C,">="&DATE(YEAR(G24),MONTH(G24),1),Input!$C:$C,"<="&EOMONTH(G24,0)) -> 0 | I24: =SUMIFS(Input!$E:$E,Input!$D:$D,"Pengeluaran",Input!$C:$C,">="&DATE(YEAR(G24),MONTH(G24),1),Input!$C:$C,"<="&EOMONTH(G24,0)) -> 0 | J24: =H24-I24 -> 0
B25: =IFERROR(INDEX($M$2:$M$21,MATCH(LARGE($O$2:$O$21,4),$O$2:$O$21,0)),"") -> Rumah | C25: =IFERROR(INDEX($N$2:$N$21,MATCH(LARGE($O$2:$O$21,4),$O$2:$O$21,0)),0) -> 2116000 | D25: =IF($D$11=0,0,C25/$D$11) -> 0.083652112 | G25: =EDATE($C$3,-8) -> 45930 | H25: =SUMIFS(Input!$E:$E,Input!$D:$D,"Pemasukan",Input!$C:$C,">="&DATE(YEAR(G25),MONTH(G25),1),Input!$C:$C,"<="&EOMONTH(G25,0)) -> 0 | I25: =SUMIFS(Input!$E:$E,Input!$D:$D,"Pengeluaran",Input!$C:$C,">="&DATE(YEAR(G25),MONTH(G25),1),Input!$C:$C,"<="&EOMONTH(G25,0)) -> 0 | J25: =H25-I25 -> 0
B26: =IFERROR(INDEX($M$2:$M$21,MATCH(LARGE($O$2:$O$21,5),$O$2:$O$21,0)),"") -> Transportasi | C26: =IFERROR(INDEX($N$2:$N$21,MATCH(LARGE($O$2:$O$21,5),$O$2:$O$21,0)),0) -> 2099485 | D26: =IF($D$11=0,0,C26/$D$11) -> 0.082999222 | G26: =EDATE($C$3,-7) -> 45961 | H26: =SUMIFS(Input!$E:$E,Input!$D:$D,"Pemasukan",Input!$C:$C,">="&DATE(YEAR(G26),MONTH(G26),1),Input!$C:$C,"<="&EOMONTH(G26,0)) -> 0 | I26: =SUMIFS(Input!$E:$E,Input!$D:$D,"Pengeluaran",Input!$C:$C,">="&DATE(YEAR(G26),MONTH(G26),1),Input!$C:$C,"<="&EOMONTH(G26,0)) -> 0 | J26: =H26-I26 -> 0
B27: =IFERROR(INDEX($M$2:$M$21,MATCH(LARGE($O$2:$O$21,6),$O$2:$O$21,0)),"") -> Skin care-beauty | C27: =IFERROR(INDEX($N$2:$N$21,MATCH(LARGE($O$2:$O$21,6),$O$2:$O$21,0)),0) -> 1340989 | D27: =IF($D$11=0,0,C27/$D$11) -> 0.053013498 | G27: =EDATE($C$3,-6) -> 45991 | H27: =SUMIFS(Input!$E:$E,Input!$D:$D,"Pemasukan",Input!$C:$C,">="&DATE(YEAR(G27),MONTH(G27),1),Input!$C:$C,"<="&EOMONTH(G27,0)) -> 0 | I27: =SUMIFS(Input!$E:$E,Input!$D:$D,"Pengeluaran",Input!$C:$C,">="&DATE(YEAR(G27),MONTH(G27),1),Input!$C:$C,"<="&EOMONTH(G27,0)) -> 0 | J27: =H27-I27 -> 0
B28: =IFERROR(INDEX($M$2:$M$21,MATCH(LARGE($O$2:$O$21,7),$O$2:$O$21,0)),"") -> Makanan | C28: =IFERROR(INDEX($N$2:$N$21,MATCH(LARGE($O$2:$O$21,7),$O$2:$O$21,0)),0) -> 1263690 | D28: =IF($D$11=0,0,C28/$D$11) -> 0.049957626 | G28: =EDATE($C$3,-5) -> 46022 | H28: =SUMIFS(Input!$E:$E,Input!$D:$D,"Pemasukan",Input!$C:$C,">="&DATE(YEAR(G28),MONTH(G28),1),Input!$C:$C,"<="&EOMONTH(G28,0)) -> 0 | I28: =SUMIFS(Input!$E:$E,Input!$D:$D,"Pengeluaran",Input!$C:$C,">="&DATE(YEAR(G28),MONTH(G28),1),Input!$C:$C,"<="&EOMONTH(G28,0)) -> 0 | J28: =H28-I28 -> 0
B29: =IFERROR(INDEX($M$2:$M$21,MATCH(LARGE($O$2:$O$21,8),$O$2:$O$21,0)),"") -> Grab/maxime | C29: =IFERROR(INDEX($N$2:$N$21,MATCH(LARGE($O$2:$O$21,8),$O$2:$O$21,0)),0) -> 1220900 | D29: =IF($D$11=0,0,C29/$D$11) -> 0.048266004 | G29: =EDATE($C$3,-4) -> 46053 | H29: =SUMIFS(Input!$E:$E,Input!$D:$D,"Pemasukan",Input!$C:$C,">="&DATE(YEAR(G29),MONTH(G29),1),Input!$C:$C,"<="&EOMONTH(G29,0)) -> 0 | I29: =SUMIFS(Input!$E:$E,Input!$D:$D,"Pengeluaran",Input!$C:$C,">="&DATE(YEAR(G29),MONTH(G29),1),Input!$C:$C,"<="&EOMONTH(G29,0)) -> 0 | J29: =H29-I29 -> 0
B30: =IFERROR(INDEX($M$2:$M$21,MATCH(LARGE($O$2:$O$21,9),$O$2:$O$21,0)),"") -> Mega-kurnia | C30: =IFERROR(INDEX($N$2:$N$21,MATCH(LARGE($O$2:$O$21,9),$O$2:$O$21,0)),0) -> 1050000 | D30: =IF($D$11=0,0,C30/$D$11) -> 0.041509791 | G30: =EDATE($C$3,-3) -> 46081 | H30: =SUMIFS(Input!$E:$E,Input!$D:$D,"Pemasukan",Input!$C:$C,">="&DATE(YEAR(G30),MONTH(G30),1),Input!$C:$C,"<="&EOMONTH(G30,0)) -> 0 | I30: =SUMIFS(Input!$E:$E,Input!$D:$D,"Pengeluaran",Input!$C:$C,">="&DATE(YEAR(G30),MONTH(G30),1),Input!$C:$C,"<="&EOMONTH(G30,0)) -> 0 | J30: =H30-I30 -> 0
B31: =IFERROR(INDEX($M$2:$M$21,MATCH(LARGE($O$2:$O$21,10),$O$2:$O$21,0)),"") -> Pakaian | C31: =IFERROR(INDEX($N$2:$N$21,MATCH(LARGE($O$2:$O$21,10),$O$2:$O$21,0)),0) -> 959145 | D31: =IF($D$11=0,0,C31/$D$11) -> 0.037918008 | G31: =EDATE($C$3,-2) -> 46112 | H31: =SUMIFS(Input!$E:$E,Input!$D:$D,"Pemasukan",Input!$C:$C,">="&DATE(YEAR(G31),MONTH(G31),1),Input!$C:$C,"<="&EOMONTH(G31,0)) -> 0 | I31: =SUMIFS(Input!$E:$E,Input!$D:$D,"Pengeluaran",Input!$C:$C,">="&DATE(YEAR(G31),MONTH(G31),1),Input!$C:$C,"<="&EOMONTH(G31,0)) -> 0 | J31: =H31-I31 -> 0
G32: =EDATE($C$3,-1) -> 46142 | H32: =SUMIFS(Input!$E:$E,Input!$D:$D,"Pemasukan",Input!$C:$C,">="&DATE(YEAR(G32),MONTH(G32),1),Input!$C:$C,"<="&EOMONTH(G32,0)) -> 0 | I32: =SUMIFS(Input!$E:$E,Input!$D:$D,"Pengeluaran",Input!$C:$C,">="&DATE(YEAR(G32),MONTH(G32),1),Input!$C:$C,"<="&EOMONTH(G32,0)) -> 0 | J32: =H32-I32 -> 0
G33: =EDATE($C$3,-0) -> 46173 | H33: =SUMIFS(Input!$E:$E,Input!$D:$D,"Pemasukan",Input!$C:$C,">="&DATE(YEAR(G33),MONTH(G33),1),Input!$C:$C,"<="&EOMONTH(G33,0)) -> 31124475 | I33: =SUMIFS(Input!$E:$E,Input!$D:$D,"Pengeluaran",Input!$C:$C,">="&DATE(YEAR(G33),MONTH(G33),1),Input!$C:$C,"<="&EOMONTH(G33,0)) -> 25295237 | J33: =H33-I33 -> 5829238
B34: FINANCIAL PULSE & DOCTOR'S NOTE
B35: Financial Pulse Score (0-100, auto) | D35: Saving Rate Score | E35: =MIN(H11/0.2,1)*100 -> 93.643957
D36: Budget Adherence Score | E36: =MAX(0,100-AVERAGE(ABS(F15),ABS(F16),ABS(F17),ABS(F18))*100) -> 88.514842
B37: PULSE SCORE | C37: =ROUND(AVERAGE(E35,E36),0) -> 91 | D37: =IF(C37>=80,"Excellent",IF(C37>=65,"Good",IF(C37>=45,"Fair","Needs Attention"))) -> Excellent
B38: Doctor's Note (auto-generated, 3 poin)
B39: =IF(F11>0,"Cashflow positif Rp"&TEXT(F11,"#,##0")&", pertahankan konsistensinya.","Cashflow negatif Rp"&TEXT(F11,"#,##0")&" — perlu evaluasi pengeluaran segera.") -> Cashflow positif Rp5,829,238, pertahankan konsistensinya.
B40: =IF(F17<-0.03,"Alokasi Protection masih "&TEXT(D17,"0%")&" (ideal "&TEXT(E17,"0%")&") — pertimbangkan menambah dana darurat/asuransi.",IF(F17>0.03,"Alokasi Protection di atas ideal, sudah cukup terlindungi.","Alokasi Protection sudah sesuai ideal.")) -> Alokasi Protection masih 2% (ideal 10%) — pertimbangkan menambah dana darurat/asuransi.
B41: =IF(F18>0.03,"Flexible + Social spending "&TEXT(D18,"0%")&" (ideal "&TEXT(E18,"0%")&") — di atas ideal, evaluasi pengeluaran gaya hidup.","Flexible + Social spending masih terkendali.") -> Flexible + Social spending 23% (ideal 10%) — di atas ideal, evaluasi pengeluaran gaya hidup.

Sheet Behavioral Financial Dashboard
B1: YFD FIRST AID — BEHAVIORAL FINANCIAL DASHBOARD | F1: Filter Periode (bulan): | G1: 3 | Q1: (helper kategori impulsif)
B2: "Bukan sekadar kemana uangmu — tapi mengapa kamu sulit memegang uang." | Q2: Admin bank | R2: =SUMIFS(Input!$E:$E,Input!$D:$D,"Pengeluaran",Input!$H:$H,"Yes",Input!$F:$F,Q2,Input!$C:$C,">="&$C$3,Input!$C:$C,"<="&$B$3) -> 0
B3: =MAX(Input!C:C) -> 46173 | C3: =EDATE(DATE(YEAR(B3),MONTH(B3),1),-(G1-1)) -> 46082 | Q3: YFD | R3: =SUMIFS(Input!$E:$E,Input!$D:$D,"Pengeluaran",Input!$H:$H,"Yes",Input!$F:$F,Q3,Input!$C:$C,">="&$C$3,Input!$C:$C,"<="&$B$3) -> 0
Q4: Sosial | R4: =SUMIFS(Input!$E:$E,Input!$D:$D,"Pengeluaran",Input!$H:$H,"Yes",Input!$F:$F,Q4,Input!$C:$C,">="&$C$3,Input!$C:$C,"<="&$B$3) -> 589100
B5: FTSA PROFILE | Q5: Grab/maxime | R5: =SUMIFS(Input!$E:$E,Input!$D:$D,"Pengeluaran",Input!$H:$H,"Yes",Input!$F:$F,Q5,Input!$C:$C,">="&$C$3,Input!$C:$C,"<="&$B$3) -> 19200
B6: Status Assessment | D6: =IF(COUNTIF(Baseline!D69:D111,"Severe Dysregulation")+COUNTIF(Baseline!D69:D111,"Moderate Dysregulation")+COUNTIF(Baseline!D69:D111,"Mild Dysregulation")+COUNTIF(Baseline!D69:D111,"Regulasi Stabil")>0,"Sudah FTSA","Belum FTSA") -> Sudah FTSA | Q6: Skin care-beauty | R6: =SUMIFS(Input!$E:$E,Input!$D:$D,"Pengeluaran",Input!$H:$H,"Yes",Input!$F:$F,Q6,Input!$C:$C,">="&$C$3,Input!$C:$C,"<="&$B$3) -> 739257
B7: Dominant Pattern | D7: =Baseline!D119 -> SSD | Q7: Networking | R7: =SUMIFS(Input!$E:$E,Input!$D:$D,"Pengeluaran",Input!$H:$H,"Yes",Input!$F:$F,Q7,Input!$C:$C,">="&$C$3,Input!$C:$C,"<="&$B$3) -> 0
B8: Co-Regulation Pattern (urutan) | D8: =Baseline!D120 -> SSD (40) > CHD (32) > ESD (24) > RVD (16) | Q8: Hiburan | R8: =SUMIFS(Input!$E:$E,Input!$D:$D,"Pengeluaran",Input!$H:$H,"Yes",Input!$F:$F,Q8,Input!$C:$C,">="&$C$3,Input!$C:$C,"<="&$B$3) -> 174000
B9: Severity (Dominant Domain) | D9: =IF(Baseline!D119="CHD",Baseline!D69,IF(Baseline!D119="RVD",Baseline!D83,IF(Baseline!D119="SSD",Baseline!D97,Baseline!D111))) -> Severe Dysregulation | Q9: Makanan | R9: =SUMIFS(Input!$E:$E,Input!$D:$D,"Pengeluaran",Input!$H:$H,"Yes",Input!$F:$F,Q9,Input!$C:$C,">="&$C$3,Input!$C:$C,"<="&$B$3) -> 1016840
B10: Date Assessment | D10: =Baseline!C5 -> 46113 | Q10: Asuransi | R10: =SUMIFS(Input!$E:$E,Input!$D:$D,"Pengeluaran",Input!$H:$H,"Yes",Input!$F:$F,Q10,Input!$C:$C,">="&$C$3,Input!$C:$C,"<="&$B$3) -> 0
Q11: Pakaian | R11: =SUMIFS(Input!$E:$E,Input!$D:$D,"Pengeluaran",Input!$H:$H,"Yes",Input!$F:$F,Q11,Input!$C:$C,">="&$C$3,Input!$C:$C,"<="&$B$3) -> 813145
B12: MOOD DISTRIBUTION | G12: NEED vs WANT | Q12: INVESTASI | R12: =SUMIFS(Input!$E:$E,Input!$D:$D,"Pengeluaran",Input!$H:$H,"Yes",Input!$F:$F,Q12,Input!$C:$C,">="&$C$3,Input!$C:$C,"<="&$B$3) -> 0
B13: Mood | C13: Jumlah Transaksi | D13: % dari Total | G13: Tipe | H13: Jumlah | I13: % | Q13: Persembahan | R13: =SUMIFS(Input!$E:$E,Input!$D:$D,"Pengeluaran",Input!$H:$H,"Yes",Input!$F:$F,Q13,Input!$C:$C,">="&$C$3,Input!$C:$C,"<="&$B$3) -> 0
B14: Happy | C14: =COUNTIFS(Input!$I:$I,B14,Input!$D:$D,"Pengeluaran",Input!$C:$C,">="&$C$3,Input!$C:$C,"<="&$B$3) -> 38 | D14: =IF(SUM($C$14:$C$19)=0,0,C14/SUM($C$14:$C$19)) -> 0.31404959 | G14: Need | H14: =COUNTIFS(Input!$G:$G,G14,Input!$D:$D,"Pengeluaran",Input!$C:$C,">="&$C$3,Input!$C:$C,"<="&$B$3) -> 83 | I14: =IF(SUM($H$14:$H$15)=0,0,H14/SUM($H$14:$H$15)) -> 0.68595041 | Q14: Subscription | R14: =SUMIFS(Input!$E:$E,Input!$D:$D,"Pengeluaran",Input!$H:$H,"Yes",Input!$F:$F,Q14,Input!$C:$C,">="&$C$3,Input!$C:$C,"<="&$B$3) -> 0
B15: Neutral | C15: =COUNTIFS(Input!$I:$I,B15,Input!$D:$D,"Pengeluaran",Input!$C:$C,">="&$C$3,Input!$C:$C,"<="&$B$3) -> 60 | D15: =IF(SUM($C$14:$C$19)=0,0,C15/SUM($C$14:$C$19)) -> 0.49586777 | G15: Wants | H15: =COUNTIFS(Input!$G:$G,G15,Input!$D:$D,"Pengeluaran",Input!$C:$C,">="&$C$3,Input!$C:$C,"<="&$B$3) -> 38 | I15: =IF(SUM($H$14:$H$15)=0,0,H15/SUM($H$14:$H$15)) -> 0.31404959 | Q15: Rumah | R15: =SUMIFS(Input!$E:$E,Input!$D:$D,"Pengeluaran",Input!$H:$H,"Yes",Input!$F:$F,Q15,Input!$C:$C,">="&$C$3,Input!$C:$C,"<="&$B$3) -> 0
B16: Sad | C16: =COUNTIFS(Input!$I:$I,B16,Input!$D:$D,"Pengeluaran",Input!$C:$C,">="&$C$3,Input!$C:$C,"<="&$B$3) -> 2 | D16: =IF(SUM($C$14:$C$19)=0,0,C16/SUM($C$14:$C$19)) -> 0.016528926 | Q16: Tagihan | R16: =SUMIFS(Input!$E:$E,Input!$D:$D,"Pengeluaran",Input!$H:$H,"Yes",Input!$F:$F,Q16,Input!$C:$C,">="&$C$3,Input!$C:$C,"<="&$B$3) -> 0
B17: Stressed | C17: =COUNTIFS(Input!$I:$I,B17,Input!$D:$D,"Pengeluaran",Input!$C:$C,">="&$C$3,Input!$C:$C,"<="&$B$3) -> 9 | D17: =IF(SUM($C$14:$C$19)=0,0,C17/SUM($C$14:$C$19)) -> 0.074380165 | Q17: Pulsa | R17: =SUMIFS(Input!$E:$E,Input!$D:$D,"Pengeluaran",Input!$H:$H,"Yes",Input!$F:$F,Q17,Input!$C:$C,">="&$C$3,Input!$C:$C,"<="&$B$3) -> 0
B18: Angry | C18: =COUNTIFS(Input!$I:$I,B18,Input!$D:$D,"Pengeluaran",Input!$C:$C,">="&$C$3,Input!$C:$C,"<="&$B$3) -> 2 | D18: =IF(SUM($C$14:$C$19)=0,0,C18/SUM($C$14:$C$19)) -> 0.016528926 | Q18: Transportasi | R18: =SUMIFS(Input!$E:$E,Input!$D:$D,"Pengeluaran",Input!$H:$H,"Yes",Input!$F:$F,Q18,Input!$C:$C,">="&$C$3,Input!$C:$C,"<="&$B$3) -> 0
B19: Tired | C19: =COUNTIFS(Input!$I:$I,B19,Input!$D:$D,"Pengeluaran",Input!$C:$C,">="&$C$3,Input!$C:$C,"<="&$B$3) -> 10 | D19: =IF(SUM($C$14:$C$19)=0,0,C19/SUM($C$14:$C$19)) -> 0.082644628 | Q19: Mega-kurnia | R19: =SUMIFS(Input!$E:$E,Input!$D:$D,"Pengeluaran",Input!$H:$H,"Yes",Input!$F:$F,Q19,Input!$C:$C,">="&$C$3,Input!$C:$C,"<="&$B$3) -> 500000
Q20: Hadiah | R20: =SUMIFS(Input!$E:$E,Input!$D:$D,"Pengeluaran",Input!$H:$H,"Yes",Input!$F:$F,Q20,Input!$C:$C,">="&$C$3,Input!$C:$C,"<="&$B$3) -> 0
B21: IMPULSIVE SPENDING | Q21: Lale | R21: =SUMIFS(Input!$E:$E,Input!$D:$D,"Pengeluaran",Input!$H:$H,"Yes",Input!$F:$F,Q21,Input!$C:$C,">="&$C$3,Input!$C:$C,"<="&$B$3) -> 0
B22: Jumlah Transaksi Impulsif | D22: Total Nominal Impulsif | F22: % dari Total Transaksi | H22: Top Kategori Impulsif
B23: =COUNTIFS(Input!$H:$H,"Yes",Input!$D:$D,"Pengeluaran",Input!$C:$C,">="&$C$3,Input!$C:$C,"<="&$B$3) -> 36 | D23: =SUMIFS(Input!$E:$E,Input!$H:$H,"Yes",Input!$D:$D,"Pengeluaran",Input!$C:$C,">="&$C$3,Input!$C:$C,"<="&$B$3) -> 3851542 | F23: =IFERROR(B23/COUNTIFS(Input!$D:$D,"Pengeluaran",Input!$C:$C,">="&$C$3,Input!$C:$C,"<="&$B$3),0) -> 0.29752066 | H23: =IFERROR(INDEX($Q$2:$Q$21,MATCH(MAX($R$2:$R$21),$R$2:$R$21,0)),"-") -> Makanan
B25: MOOD SPENDING MATRIX
B26: Mood | C26: Transaksi | D26: Total Spending | E26: Average / Transaksi | F26: % Impulsif
B27: Happy | C27: =COUNTIFS(Input!$I:$I,B27,Input!$D:$D,"Pengeluaran",Input!$C:$C,">="&$C$3,Input!$C:$C,"<="&$B$3) -> 38 | D27: =SUMIFS(Input!$E:$E,Input!$I:$I,B27,Input!$D:$D,"Pengeluaran",Input!$C:$C,">="&$C$3,Input!$C:$C,"<="&$B$3) -> 5268941 | E27: =IFERROR(D27/C27,0) -> 138656.34 | F27: =IFERROR(COUNTIFS(Input!$I:$I,B27,Input!$H:$H,"Yes",Input!$D:$D,"Pengeluaran",Input!$C:$C,">"&$C$3,Input!$C:$C,"<"&$B$3)/C27,0) -> 0.36842105
B28: Neutral | C28: =COUNTIFS(Input!$I:$I,B28,Input!$D:$D,"Pengeluaran",Input!$C:$C,">="&$C$3,Input!$C:$C,"<="&$B$3) -> 60 | D28: =SUMIFS(Input!$E:$E,Input!$I:$I,B28,Input!$D:$D,"Pengeluaran",Input!$C:$C,">="&$C$3,Input!$C:$C,"<="&$B$3) -> 8583499 | E28: =IFERROR(D28/C28,0) -> 143058.32 | F28: =IFERROR(COUNTIFS(Input!$I:$I,B28,Input!$H:$H,"Yes",Input!$D:$D,"Pengeluaran",Input!$C:$C,">"&$C$3,Input!$C:$C,"<"&$B$3)/C28,0) -> 0.066666667
B29: Sad | C29: =COUNTIFS(Input!$I:$I,B29,Input!$D:$D,"Pengeluaran",Input!$C:$C,">="&$C$3,Input!$C:$C,"<="&$B$3) -> 2 | D29: =SUMIFS(Input!$E:$E,Input!$I:$I,B29,Input!$D:$D,"Pengeluaran",Input!$C:$C,">="&$C$3,Input!$C:$C,"<="&$B$3) -> 3647629 | E29: =IFERROR(D29/C29,0) -> 1823814.5 | F29: =IFERROR(COUNTIFS(Input!$I:$I,B29,Input!$H:$H,"Yes",Input!$D:$D,"Pengeluaran",Input!$C:$C,">"&$C$3,Input!$C:$C,"<"&$B$3)/C29,0) -> 0.5
B30: Stressed | C30: =COUNTIFS(Input!$I:$I,B30,Input!$D:$D,"Pengeluaran",Input!$C:$C,">="&$C$3,Input!$C:$C,"<="&$B$3) -> 9 | D30: =SUMIFS(Input!$E:$E,Input!$I:$I,B30,Input!$D:$D,"Pengeluaran",Input!$C:$C,">="&$C$3,Input!$C:$C,"<="&$B$3) -> 1037128 | E30: =IFERROR(D30/C30,0) -> 115236.44 | F30: =IFERROR(COUNTIFS(Input!$I:$I,B30,Input!$H:$H,"Yes",Input!$D:$D,"Pengeluaran",Input!$C:$C,">"&$C$3,Input!$C:$C,"<"&$B$3)/C30,0) -> 0.66666667
B31: Angry | C31: =COUNTIFS(Input!$I:$I,B31,Input!$D:$D,"Pengeluaran",Input!$C:$C,">="&$C$3,Input!$C:$C,"<="&$B$3) -> 2 | D31: =SUMIFS(Input!$E:$E,Input!$I:$I,B31,Input!$D:$D,"Pengeluaran",Input!$C:$C,">="&$C$3,Input!$C:$C,"<="&$B$3) -> 6390000 | E31: =IFERROR(D31/C31,0) -> 3195000 | F31: =IFERROR(COUNTIFS(Input!$I:$I,B31,Input!$H:$H,"Yes",Input!$D:$D,"Pengeluaran",Input!$C:$C,">"&$C$3,Input!$C:$C,"<"&$B$3)/C31,0) -> 0
B32: Tired | C32: =COUNTIFS(Input!$I:$I,B32,Input!$D:$D,"Pengeluaran",Input!$C:$C,">="&$C$3,Input!$C:$C,"<="&$B$3) -> 10 | D32: =SUMIFS(Input!$E:$E,Input!$I:$I,B32,Input!$D:$D,"Pengeluaran",Input!$C:$C,">="&$C$3,Input!$C:$C,"<="&$B$3) -> 368040 | E32: =IFERROR(D32/C32,0) -> 36804 | F32: =IFERROR(COUNTIFS(Input!$I:$I,B32,Input!$H:$H,"Yes",Input!$D:$D,"Pengeluaran",Input!$C:$C,">"&$C$3,Input!$C:$C,"<"&$B$3)/C32,0) -> 1
B34: BEHAVIORAL INSIGHT (auto, 3 poin)
B35: ="Sebagian besar transaksi impulsif terjadi saat mood "&INDEX(B27:B32,MATCH(MAX(F27:F32),F27:F32,0))&" ("&TEXT(MAX(F27:F32),"0%")&" dari transaksi saat mood itu bersifat impulsif)." -> Sebagian besar transaksi impulsif terjadi saat mood Tired (100% dari transaksi saat mood itu bersifat impulsif).
B36: ="Saat mood "&INDEX(B27:B32,MATCH(MAX(E27:E32),E27:E32,0))&", rata-rata nominal transaksi meningkat menjadi Rp"&TEXT(MAX(E27:E32),"#,##0")&" per transaksi — tertinggi dibanding mood lain." -> Saat mood Angry, rata-rata nominal transaksi meningkat menjadi Rp3,195,000 per transaksi — tertinggi dibanding mood lain.
B37: ="Mood "&INDEX(B27:B32,MATCH(MAX(C27:C32),C27:C32,0))&" paling sering menyertai transaksi ("&MAX(C27:C32)&" transaksi pada periode ini)." -> Mood Neutral paling sering menyertai transaksi (60 transaksi pada periode ini).
B39: BEHAVIORAL RECOMMENDATION
B40: Mode | D40: =D6 -> Sudah FTSA
B41: =IF(D40="Belum FTSA","Perhatikan pengeluaran saat mood "&INDEX(B27:B32,MATCH(MAX(F27:F32),F27:F32,0))&" — siapkan alternatif lebih hemat (mis. cooling-off 24 jam sebelum beli) untuk kategori "&H23&" saat energi/emosi sedang rendah.",IF(Baseline!$D$119="CHD","Personalized (Controller): batasi cek portofolio/keuangan maksimal 1x/minggu, gunakan sistem auto-invest, dan latih toleransi terhadap ketidakpastian finansial.",IF(Baseline!$D$119="RVD","Personalized (Avoider): lakukan review keuangan 15 menit/minggu, mulai investasi nominal kecil secara rutin, dan cari accountability partner untuk diskusi keuangan.",IF(Baseline!$D$119="SSD","Personalized (Overworker): tetapkan angka cukup (enough number), jadwalkan hari tanpa bekerja, dan mulai bangun passive income agar keamanan tidak hanya bersumber dari produktivitas.","Personalized (Impulsive): terapkan cooling-off 24 jam sebelum membeli barang non-esensial, gunakan cash envelope untuk pengeluaran fleksibel, dan bangun reward non-monetary sebagai pengganti belanja emosional.")))) -> Personalized (Overworker): tetapkan angka cukup (enough number), jadwalkan hari tanpa bekerja, dan mulai bangun passive income agar keamanan tidak hanya bersumber dari produktivitas.

Sheet Kategori_Mapping
A1: Kategori | B1: Bucket | C1: Tipe | D1: Alasan / Konteks Transaksi Asli | E1: CATATAN: Tabel ini adalah sumber kebenaran (source of truth) kategori → bucket. | G1: Stage | H1: Essential Living | I1: Future Building | J1: Protection | K1: Flexible + Social
A2: Gaji | B2: Income | C2: Income | D2: Pemasukan rutin — di luar bucket | E2: Saat AI kategorisasi via bot Telegram diaktifkan, AI HARUS hanya menghasilkan nilai Kategori yang ADA di kolom A tabel ini. | G2: Surviving | H2: 0.8 | I2: 0.05 | J2: 0.05 | K2: 0.1
A3: Dividen | B3: Income | C3: Income | D3: Pemasukan investasi — di luar bucket | E3: Kategori baru yang muncul dari user harus ditambahkan ke tabel ini dulu (oleh tim YFD/AI prompt design) sebelum bisa terbaca otomatis oleh dashboard. | G3: Growing | H3: 0.6 | I3: 0.2 | J3: 0.1 | K3: 0.1
A4: Lain-lain | B4: Income | C4: Income | D4: Pemasukan lain-lain — di luar bucket | G4: Steady | H4: 0.5 | I4: 0.3 | J4: 0.1 | K4: 0.1
A5: Muen | B5: Income | C5: Income | D5: Pemasukan lain-lain — di luar bucket | G5: Comfortable | H5: 0.4 | I5: 0.35 | J5: 0.1 | K5: 0.15
A6: Admin bank | B6: Essential Living | C6: Expense | D6: Biaya administrasi rekening — Pajak & Administrasi (Essential)
A7: YFD | B7: Future Building | C7: Expense | D7: Cek konteks: "Fund Adds FB", "Adds tiktok" = biaya marketing/iklan usaha YFD → Bisnis (Future Building). BUKAN pengembangan diri pribadi.
A8: Sosial | B8: Flexible + Social | C8: Expense | D8: Tip, treatment, oleh-oleh, hadiah, bantu keluarga → Dana Sosial (Flexible+Social). PERLU DICEK: ada 1 transaksi "Yankes diamed" Rp250rb — kemungkinan biaya kesehatan, bukan sosial. Mohon konfirmasi.
A9: Grab/maxime | B9: Essential Living | C9: Expense | D9: Transportasi rutin harian (kos↔lokasi kerja/aktivitas) → Essential Living
A10: Skin care-beauty | B10: Flexible + Social | C10: Expense | D10: Shopping/perawatan diri non-esensial → Flexible+Social
A11: Networking | B11: Future Building | C11: Expense | D11: Konteks: "Ketemu investor" → aktivitas bisnis → Future Building (Bisnis)
A12: Hiburan | B12: Flexible + Social | C12: Expense | D12: Entertainment → Flexible+Social
A13: Dipinjam | B13: Transfer (Excluded) | C13: Transfer | D13: Uang dipinjamkan/dipinjam — bukan pengeluaran riil, dikecualikan dari bucket
A14: Makanan | B14: Essential Living | C14: Expense | D14: Kebutuhan dasar harian → Essential Living
A15: Asuransi | B15: Protection | C15: Expense | D15: BPJS, Income Protection → Protection
A16: Pakaian | B16: Flexible + Social | C16: Expense | D16: Shopping/Fashion → Flexible+Social
A17: INVESTASI | B17: Future Building | C17: Expense | D17: Dicek: semua transaksi adalah pembelian saham (BBCA, BBRI) → Future Building murni, tidak ada top-up dana darurat tercampur
... A26: Lale | B26: Essential Living | C26: Expense | D26: Konteks: "Bensin lale" → BBM kendaraan → Essential Living
A30: DOKUMENTASI RESMI — DEFINISI BUCKET (acuan untuk AI kategorisasi & tim YFD)
A31: Arah target tiap bucket terhadap % Income:
A32: Essential Living | B32: MAKSIMAL — semakin rendah % nya, semakin sehat
A33: Future Building | B33: MINIMAL — semakin tinggi % nya, semakin sehat
A34: Protection | B34: MAKSIMAL — jangan melebihi batas ideal per stage
A35: Flexible + Social | B35: MAKSIMAL — jangan melebihi batas ideal per stage
A37: ESSENTIAL LIVING — pengeluaran mempertahankan kehidupan & kemampuan bekerja hari ini
A38: • Tempat Tinggal: sewa/cicilan rumah utama, IPL, listrik, air, internet rumah, gas
A39: • Makanan: belanja dapur, makan harian, air minum
A40: • Transportasi: BBM, tol, parkir, transportasi umum, ojol untuk aktivitas rutin
A41: • Komunikasi: pulsa, paket data, internet HP
A42: • Kesehatan: medical check up, dokter, obat, lab, vitamin rutin
A43: • Pendidikan Wajib: uang sekolah, UKT, buku wajib
A44: • Anak/Keluarga: susu bayi, popok, kebutuhan sekolah anak
A45: • Pajak & Administrasi: pajak kendaraan/rumah, admin bank
A47: FUTURE BUILDING — meningkatkan nilai aset / kapasitas menghasilkan uang di masa depan
A48: • Investasi: saham, reksa dana, obligasi, emas, deposito, crypto (opsional)
A49: • Pengembangan Diri: seminar, simposium, workshop, sertifikasi, pelatihan, kursus, buku, conference, riset
... A69: • Mobil — DP mobil pribadi: Asset (dicatat di Baseline, bukan transaksi bucket). Cicilan utk kebutuhan utama: Essential Living.
